polars_plugin_option_pricing-0.1.0.dist-info/METADATA
polars_plugin_option_pricing-0.1.0.dist-info/WHEEL
polars_plugin_option_pricing/_typing.py
polars_plugin_option_pricing/_util.py
polars_plugin_option_pricing/__init__.py
src/black_scholes.rs
src/implied_vol.rs
src/lib.rs
polars_plugin_option_pricing/_rust.abi3.so
polars_plugin_option_pricing-0.1.0.dist-info/RECORD
