Metadata-Version: 2.3
Name: polars_plugin_option_pricing
Version: 0.1.0
Classifier: Development Status :: 4 - Beta
Classifier: License :: OSI Approved :: MIT License
Classifier: Intended Audience :: Developers
Classifier: Programming Language :: Python :: 3
Classifier: Programming Language :: Python :: 3.10
Classifier: Programming Language :: Python :: 3.11
Classifier: Programming Language :: Python :: 3.12
Classifier: Operating System :: POSIX
Classifier: Operating System :: MacOS :: MacOS X
Classifier: Operating System :: Microsoft :: Windows
Requires-Dist: pytest ; extra == 'dev'
Provides-Extra: dev
Summary: black scholes and implied vol calc
Keywords: polars,plugin,blackscholes
Author-email: firstname lastname <author@gmail.com>
License: MIT
Requires-Python: >=3.10
Project-URL: repository, https://github.com/oscar6echo/polars-plugin-explo.git
